playing_cards/__init__.py
playing_cards/main.py
card_game_simulation-0.0.1.dist-info/LICENSE
card_game_simulation-0.0.1.dist-info/METADATA
card_game_simulation-0.0.1.dist-info/WHEEL
card_game_simulation-0.0.1.dist-info/top_level.txt
card_game_simulation-0.0.1.dist-info/RECORD
