Metadata-Version: 2.1
Name: card-game-simulation
Version: 0.0.1
Summary: Classes that model playing cards and games played with them
Home-page: https://github.com/areese801/playing-cards
Author: Adam Reese
Author-email: Adam Reese <areese801@gmail.com>
License: MIT License        
Project-URL: Homepage, https://github.com/areese801/playing-cards
Project-URL: Bug Tracker, https://github.com/areese801/playing-cards/issues
Classifier: Programming Language :: Python :: 3
Classifier: License :: OSI Approved :: MIT License
Classifier: Operating System :: OS Independent
Requires-Python: >=3.8
License-File: LICENSE
